etplib/__init__.py
etplib/adc.py
etplib/gpio.py
etplib/i2c.py
etplib/lib.py
etplib/pwm.py
etplib/spi.py
etplib/version.py
etplib-0.2.1.dist-info/LICENSE
etplib-0.2.1.dist-info/METADATA
etplib-0.2.1.dist-info/WHEEL
etplib-0.2.1.dist-info/top_level.txt
etplib-0.2.1.dist-info/RECORD
